privateclasses/__init__.py
privateclasses/__main__.py
privateclasses/tests/__init__.py
privateclasses/tests/test_1984.py
privateclasses-0.0.1.dev0.dist-info/LICENSE.txt
privateclasses-0.0.1.dev0.dist-info/METADATA
privateclasses-0.0.1.dev0.dist-info/WHEEL
privateclasses-0.0.1.dev0.dist-info/top_level.txt
privateclasses-0.0.1.dev0.dist-info/RECORD
